Workbook

Sheet PRODUCT DETAILS
A1: PRODUCT DETAILS
A2: PRODUCT_ID | B2: PRODUCT NAME | C2: CATEGORY | D2: PRICE | E2: GST | F2: WAREHOUSE
A3: P101 | B3: Laptop | C3: Electronics | D3: =RANDBETWEEN(50000,90000) -> 63101 | E3: 0.18 | F3: A1
A4: P102 | B4: Mouse | C4: Accessories | D4: =RANDBETWEEN(50000,90000) -> 75197 | E4: 0.18 | F4: A2
A5: P103 | B5: Keyboard | C5: Accessories | D5: =RANDBETWEEN(50000,90000) -> 87843 | E5: 0.18 | F5: A2
A6: P104 | B6: Monitor | C6: Electronics | D6: =RANDBETWEEN(50000,90000) -> 59072 | E6: 0.18 | F6: B1
A7: P105 | B7: Printer | C7: Office | D7: =RANDBETWEEN(50000,90000) -> 77772 | E7: 0.18 | F7: B2
A8: P106 | B8: Speaker | C8: Electronics | D8: =RANDBETWEEN(50000,90000) -> 66344 | E8: 0.18 | F8: C1
A9: P107 | B9: Webcam | C9: Electronics | D9: =RANDBETWEEN(50000,90000) -> 58097 | E9: 0.18 | F9: C2
A10: P108 | B10: SSD | C10: Storage | D10: =RANDBETWEEN(50000,90000) -> 70698 | E10: 0.18 | F10: D1
A11: P109 | B11: CPU | C11: Accessories | D11: =RANDBETWEEN(50000,90000) -> 60733 | E11: 0.18 | F11: B2
A12: P110 | B12: TV | C12: Electronics | D12: =RANDBETWEEN(50000,90000) -> 58253 | E12: 0.18 | F12: A1

Sheet SALES DETAILS
A1: SALES DETAILS | O1: FUNCTIONS
A2: ORDER NO | B2: PRODUCT_ID | C2: QUANTITY | D2: PRODUCT NAME | E2: PRODUCT CODE | F2: ORDER REFERENCE | G2: CATEGORY | H2: PRICE | I2: GST% | J2: TOTAL AMOUNT | K2: GST AMOUNT | L2: FINAL BILL | M2: WAREHOUSE | O2: MATCH | P2: INDEX | Q2: INDEX + MATCH
A3: 001 | B3: P101 | C3: =RANDBETWEEN(1,7) -> 2 | D3: =IFERROR(VLOOKUP(B3,'PRODUCT DETAILS'!$A$2:$F$11,2,FALSE),"PRODUCT NOT FOUND") -> Laptop | E3: =UPPER(LEFT(D3,3)) -> LAP | F3: =_xlfn.CONCAT("ORD-",B3,"-",TEXT(A3,"000")) -> ORD-P101-001 | G3: =VLOOKUP(B3,'PRODUCT DETAILS'!A2:F12,3,0) -> Electronics | H3: =VLOOKUP(B3,'PRODUCT DETAILS'!A3:F12,4,0) -> 63101 | I3: =VLOOKUP(B3,'PRODUCT DETAILS'!A3:F12,5,0) -> 0.18 | J3: =C3*H3 -> 126202 | K3: =J3*I3 -> 22716.36 | L3: =J3+K3 -> 148918.36 | M3: =VLOOKUP(B3,'PRODUCT DETAILS'!A3:F12,6,0) -> A1 | O3: =MATCH("P105",'PRODUCT DETAILS'!A2:A11,0) -> 6 | P3: =INDEX('PRODUCT DETAILS'!D2:D11,8) -> 58097 | Q3: {=INDEX('PRODUCT DETAILS'!F2:F11,MATCH(B2,'PRODUCT DETAILS'!A2:A11,0))} -> WAREHOUSE
A4: 002 | B4: P103 | C4: =RANDBETWEEN(1,7) -> 6 | D4: =IFERROR(VLOOKUP(B4,'PRODUCT DETAILS'!$A$2:$F$11,2,FALSE),"PRODUCT NOT FOUND") -> Keyboard | E4: =UPPER(LEFT(D4,3)) -> KEY | F4: =_xlfn.CONCAT("ORD-",B4,"-",TEXT(A4,"000")) -> ORD-P103-002 | G4: =VLOOKUP(B4,'PRODUCT DETAILS'!A3:F13,3,0) -> Accessories | H4: =VLOOKUP(B4,'PRODUCT DETAILS'!A4:F13,4,0) -> 87843 | I4: =VLOOKUP(B4,'PRODUCT DETAILS'!A4:F13,5,0) -> 0.18 | J4: =C4*H4 -> 527058 | K4: =J4*I4 -> 94870.44 | L4: =J4+K4 -> 621928.44 | M4: =VLOOKUP(B4,'PRODUCT DETAILS'!A4:F13,6,0) -> A2
A5: 003 | B5: P105 | C5: =RANDBETWEEN(1,7) -> 6 | D5: =IFERROR(VLOOKUP(B5,'PRODUCT DETAILS'!$A$2:$F$11,2,FALSE),"PRODUCT NOT FOUND") -> Printer | E5: =UPPER(LEFT(D5,3)) -> PRI | F5: =_xlfn.CONCAT("ORD-",B5,"-",TEXT(A5,"000")) -> ORD-P105-003 | G5: =VLOOKUP(B5,'PRODUCT DETAILS'!A4:F14,3,0) -> Office | H5: =VLOOKUP(B5,'PRODUCT DETAILS'!A5:F14,4,0) -> 77772 | I5: =VLOOKUP(B5,'PRODUCT DETAILS'!A5:F14,5,0) -> 0.18 | J5: =C5*H5 -> 466632 | K5: =J5*I5 -> 83993.76 | L5: =J5+K5 -> 550625.76 | M5: =VLOOKUP(B5,'PRODUCT DETAILS'!A5:F14,6,0) -> B2
A6: 004 | B6: P108 | C6: =RANDBETWEEN(1,7) -> 4 | D6: =IFERROR(VLOOKUP(B6,'PRODUCT DETAILS'!$A$2:$F$11,2,FALSE),"PRODUCT NOT FOUND") -> SSD | E6: =UPPER(LEFT(D6,3)) -> SSD | F6: =_xlfn.CONCAT("ORD-",B6,"-",TEXT(A6,"000")) -> ORD-P108-004 | G6: =VLOOKUP(B6,'PRODUCT DETAILS'!A5:F15,3,0) -> Storage | H6: =VLOOKUP(B6,'PRODUCT DETAILS'!A6:F15,4,0) -> 70698 | I6: =VLOOKUP(B6,'PRODUCT DETAILS'!A6:F15,5,0) -> 0.18 | J6: =C6*H6 -> 282792 | K6: =J6*I6 -> 50902.56 | L6: =J6+K6 -> 333694.56 | M6: =VLOOKUP(B6,'PRODUCT DETAILS'!A6:F15,6,0) -> D1 | O6: FINAL BILL
A7: 005 | B7: P110 | C7: =RANDBETWEEN(1,7) -> 4 | D7: =IFERROR(VLOOKUP(B7,'PRODUCT DETAILS'!A2:F12,2,FALSE),"PRODUCT NOT FOUND") -> TV | E7: =UPPER(LEFT(D7,3)) -> TV | F7: =_xlfn.CONCAT("ORD-",B7,"-",TEXT(A7,"000")) -> ORD-P110-005 | G7: =VLOOKUP(B7,'PRODUCT DETAILS'!A6:F16,3,0) -> Electronics | H7: =VLOOKUP(B7,'PRODUCT DETAILS'!A7:F16,4,0) -> 58253 | I7: =VLOOKUP(B7,'PRODUCT DETAILS'!A7:F16,5,0) -> 0.18 | J7: =C7*H7 -> 233012 | K7: =J7*I7 -> 41942.16 | L7: =J7+K7 -> 274954.16 | M7: =VLOOKUP(B7,'PRODUCT DETAILS'!A7:F16,6,0) -> A1 | O7: HIGHEST BILL | P7: LOWEST BILL | Q7: AVERAGE BILL | R7: TOTAL REVENUE
A8: 006 | B8: P104 | C8: =RANDBETWEEN(1,7) -> 5 | D8: =IFERROR(VLOOKUP(B8,'PRODUCT DETAILS'!$A$2:$F$11,2,FALSE),"PRODUCT NOT FOUND") -> Monitor | E8: =UPPER(LEFT(D8,3)) -> MON | F8: =_xlfn.CONCAT("ORD-",B8,"-",TEXT(A8,"000")) -> ORD-P104-006 | G8: =VLOOKUP(B8,'PRODUCT DETAILS'!A2:F12,3,0) -> Electronics | H8: =VLOOKUP(B8,'PRODUCT DETAILS'!A2:F12,4,0) -> 59072 | I8: =VLOOKUP(B8,'PRODUCT DETAILS'!A3:F12,5,0) -> 0.18 | J8: =C8*H8 -> 295360 | K8: =J8*I8 -> 53164.8 | L8: =J8+K8 -> 348524.8 | M8: =VLOOKUP(B8,'PRODUCT DETAILS'!A3:F12,6,0) -> B1 | O8: =MAX(J3:J12) -> 527058 | P8: =MIN(J3:J12) -> 66344 | Q8: =AVERAGE(J3:J12) -> 258211.7 | R8: =SUM(J3:J12) -> 2582117
A9: 007 | B9: P102 | C9: =RANDBETWEEN(1,7) -> 3 | D9: =IFERROR(VLOOKUP(B9,'PRODUCT DETAILS'!$A$2:$F$11,2,FALSE),"PRODUCT NOT FOUND") -> Mouse | E9: =UPPER(LEFT(D9,3)) -> MOU | F9: =_xlfn.CONCAT("ORD-",B9,"-",TEXT(A9,"000")) -> ORD-P102-007 | G9: =VLOOKUP(B9,'PRODUCT DETAILS'!A3:F13,3,0) -> Accessories | H9: =VLOOKUP(B9,'PRODUCT DETAILS'!A3:F13,4,0) -> 75197 | I9: =VLOOKUP(B9,'PRODUCT DETAILS'!A4:F13,5,0) -> 0.18 | J9: =C9*H9 -> 225591 | K9: =J9*I9 -> 40606.38 | L9: =J9+K9 -> 266197.38 | M9: =VLOOKUP(B9,'PRODUCT DETAILS'!A4:F13,6,0) -> A2
A10: 008 | B10: P106 | C10: =RANDBETWEEN(1,7) -> 1 | D10: =IFERROR(VLOOKUP(B10,'PRODUCT DETAILS'!$A$2:$F$11,2,FALSE),"PRODUCT NOT FOUND") -> Speaker | E10: =UPPER(LEFT(D10,3)) -> SPE | F10: =_xlfn.CONCAT("ORD-",B10,"-",TEXT(A10,"000")) -> ORD-P106-008 | G10: =VLOOKUP(B10,'PRODUCT DETAILS'!A4:F14,3,0) -> Electronics | H10: =VLOOKUP(B10,'PRODUCT DETAILS'!A4:F14,4,0) -> 66344 | I10: =VLOOKUP(B10,'PRODUCT DETAILS'!A5:F14,5,0) -> 0.18 | J10: =C10*H10 -> 66344 | K10: =J10*I10 -> 11941.92 | L10: =J10+K10 -> 78285.92 | M10: =VLOOKUP(B10,'PRODUCT DETAILS'!A5:F14,6,0) -> C1
A11: 009 | B11: P109 | C11: =RANDBETWEEN(1,7) -> 4 | D11: =IFERROR(VLOOKUP(B11,'PRODUCT DETAILS'!$A$2:$F$11,2,FALSE),"PRODUCT NOT FOUND") -> CPU | E11: =UPPER(LEFT(D11,3)) -> CPU | F11: =_xlfn.CONCAT("ORD-",B11,"-",TEXT(A11,"000")) -> ORD-P109-009 | G11: =VLOOKUP(B11,'PRODUCT DETAILS'!A5:F15,3,0) -> Accessories | H11: =VLOOKUP(B11,'PRODUCT DETAILS'!A5:F15,4,0) -> 60733 | I11: =VLOOKUP(B11,'PRODUCT DETAILS'!A6:F15,5,0) -> 0.18 | J11: =C11*H11 -> 242932 | K11: =J11*I11 -> 43727.76 | L11: =J11+K11 -> 286659.76 | M11: =VLOOKUP(B11,'PRODUCT DETAILS'!A6:F15,6,0) -> B2
A12: 010 | B12: P107 | C12: =RANDBETWEEN(1,7) -> 2 | D12: =IFERROR(VLOOKUP(B12,'PRODUCT DETAILS'!$A$2:$F$11,2,FALSE),"PRODUCT NOT FOUND") -> Webcam | E12: =UPPER(LEFT(D12,3)) -> WEB | F12: =_xlfn.CONCAT("ORD-",B12,"-",TEXT(A12,"000")) -> ORD-P107-010 | G12: =VLOOKUP(B12,'PRODUCT DETAILS'!A6:F16,3,0) -> Electronics | H12: =VLOOKUP(B12,'PRODUCT DETAILS'!A6:F16,4,0) -> 58097 | I12: =VLOOKUP(B12,'PRODUCT DETAILS'!A7:F16,5,0) -> 0.18 | J12: =C12*H12 -> 116194 | K12: =J12*I12 -> 20914.92 | L12: =J12+K12 -> 137108.92 | M12: =VLOOKUP(B12,'PRODUCT DETAILS'!A7:F16,6,0) -> C2
